pipelinewise/__init__.py
pipelinewise-1.0.0.dist-info/METADATA
pipelinewise-1.0.0.dist-info/WHEEL
pipelinewise-1.0.0.dist-info/top_level.txt
pipelinewise-1.0.0.dist-info/RECORD
