Metadata-Version: 2.1
Name: pipelinewise
Version: 1.0.0
Summary: Dependency confusion
Home-page: UNKNOWN
Author: gmanhaes
Author-email: gmanhaes0@gmail.com
License: UNKNOWN
Platform: UNKNOWN
Requires-Dist: requests
